pydantic_universal_settings/__init__.py
pydantic_universal_settings/cli.py
pydantic_universal_settings/main.py
pydantic_universal_settings-0.1.5.dist-info/WHEEL
pydantic_universal_settings-0.1.5.dist-info/METADATA
pydantic_universal_settings-0.1.5.dist-info/RECORD
