Metadata-Version: 2.1
Name: pydantic-universal-settings
Version: 0.1.5
Summary: 
License: MIT
Author: tc-imba
Author-email: liuyh970615@gmail.com
Requires-Python: >=3.6.2,<4.0.0
Classifier: License :: OSI Approved :: MIT License
Classifier: Programming Language :: Python :: 3
Classifier: Programming Language :: Python :: 3.10
Classifier: Programming Language :: Python :: 3.7
Classifier: Programming Language :: Python :: 3.8
Classifier: Programming Language :: Python :: 3.9
Requires-Dist: click-option-group (>=0.5.3,<0.6.0)
Requires-Dist: psutil (>=5.8.0,<6.0.0)
Requires-Dist: pydantic[dotenv] (>=1.8.2,<2.0.0)
